CHANGELOG.txt
LICENSE.txt
MANIFEST.in
README.txt
ez_setup.py
setup.cfg
setup.py
StringConvert.egg-info/PKG-INFO
StringConvert.egg-info/SOURCES.txt
StringConvert.egg-info/dependency_links.txt
StringConvert.egg-info/entry_points.txt
StringConvert.egg-info/not-zip-safe
StringConvert.egg-info/requires.txt
StringConvert.egg-info/top_level.txt
doc/Makefile
doc/index.txt
doc/source/api.rst
doc/source/conf.py
doc/source/index.rst
doc/source/manual.rst
example/README.txt
stringconvert/__init__.py
stringconvert/email.py
stringconvert/regex.py
stringconvert/url.py
test/README.txt
test/doc.py