Metadata-Version: 1.0
Name: StringConvert
Version: 0.3.2
Summary: Convert common objects to and from Python strings using ConversionKit
Home-page: http://jimmyg.org/work/code/stringconvert/index.html
Author: James Gardner
Author-email: UNKNOWN
License: GNU AGPLv3
Platform: UNKNOWN
Classifier: Development Status :: 3 - Alpha
Classifier: License :: OSI Approved :: GNU Affero General Public License v3
Classifier: Programming Language :: Python :: 2
Classifier: Topic :: Software Development :: Libraries :: Python Modules
